moonwalking/LendingBlockToken.json
moonwalking/__init__.py
moonwalking/main.py
moonwalking/settings.py
moonwalking/testing.py
moonwalking/utils.py
moonwalking/wallets.py
moonwalking/blocks/__init__.py
moonwalking/blocks/base.py
moonwalking/blocks/bitcoin_generic.py
moonwalking/blocks/ccyhelper.py
moonwalking/blocks/eth_generic.py
moonwalking/blocks/exc.py
moonwalking/blocks/fee.py
moonwalking-0.1.4.dist-info/METADATA
moonwalking-0.1.4.dist-info/WHEEL
moonwalking-0.1.4.dist-info/top_level.txt
moonwalking-0.1.4.dist-info/RECORD
