Metadata-Version: 2.1
Name: moonwalking
Version: 0.1.4
Summary: 
Requires-Dist: aiohttp
Requires-Dist: python-dotenv
Requires-Dist: eth-abi (==1.2.0)
Requires-Dist: eth-account (==0.3.0)
Requires-Dist: pysha3 (==1.0.2)
Requires-Dist: python-bitcoinlib (==0.10.1)
Requires-Dist: pycoin (==0.80)
Requires-Dist: bitcash (==0.5.2)
